nrfregtool/__init__.py
nrfregtool/__main__.py
nrfregtool/_cli.py
nrfregtool/_common.py
nrfregtool/_svd_util.py
nrfregtool/platform.py
nrfregtool/uicr_migrate.py
nrfregtool/resources/__init__.py
nrfregtool/resources/nrf54h20_periphconf_defaults.hex
nrfregtool/resources/uicr.svd
nrfregtool/uicr/__init__.py
nrfregtool/uicr/_builder.py
nrfregtool/uicr/_common.py
nrfregtool/zephyr/__init__.py
nrfregtool/zephyr/uicr_compile.py
nrf_regtool-9.2.1.dist-info/METADATA
nrf_regtool-9.2.1.dist-info/WHEEL
nrf_regtool-9.2.1.dist-info/entry_points.txt
nrf_regtool-9.2.1.dist-info/licenses/LICENSE
nrf_regtool-9.2.1.dist-info/RECORD
