Metadata-Version: 2.4
Name: nrf-regtool
Version: 9.2.1
Summary: Generate register content for memory-mapped peripherals.
Project-URL: homepage, https://www.nordicsemi.com
Author: Nordic Semiconductor ASA
License: 
License-File: LICENSE
Classifier: Development Status :: 5 - Production/Stable
Classifier: License :: OSI Approved :: Apache Software License
Classifier: Programming Language :: Python :: 3
Classifier: Topic :: Software Development :: Build Tools
Requires-Python: >=3.10
Requires-Dist: intelhex
Requires-Dist: svada~=2.2.0
Provides-Extra: cli
Requires-Dist: pydantic>=2.0; extra == 'cli'
Requires-Dist: tomlkit; extra == 'cli'
